{
    "SPDXID": "SPDXRef-DOCUMENT",
    "creationInfo": {
        "created": "2025-02-05T13:51:47Z",
        "creators": [
            "Tool: fossology-4.4.0.117",
            "Person: fossy"
        ],
        "licenseListVersion": "3.22",
        "comment": "\nThis document was created using license information and a generator from Fossology.\n"
    },
    "dataLicense": "CC0-1.0",
    "name": "/srv/fossology/repository/report",
    "spdxVersion": "SPDX-2.3",
    "documentNamespace": "http://ls-kube4/repo/SPDX2TV_rauc-conf.tar.gz_1738763507.spdx",
    "packages": [
        {
            "SPDXID": "SPDXRef-upload144",
            "checksums": [
                {
                    "algorithm": "SHA1",
                    "checksumValue": "660bc570c70f5c6be6667b70f7e0578df6b9b640"
                },
                {
                    "algorithm": "SHA256",
                    "checksumValue": "726f2c31fd6dcbc40d818e8b60c7aaa6499bc891405ae4bd99e5520b2ec8703d"
                },
                {
                    "algorithm": "MD5",
                    "checksumValue": "5eaf8b77b5778c50271bf0d0f1d66f18"
                }
            ],
            "copyrightText": "NOASSERTION",
            "downloadLocation": "NOASSERTION",
            "filesAnalyzed": true,
            "licenseComments": " licenseInfoInFile determined by Scanners:\n - nomos (\"4.4.0.117\".f9539e)\n - monk (\"4.4.0.117\".f9539e)\n - ojo (\"4.4.0.117\".f9539e) ",
            "licenseConcluded": "MIT",
            "licenseDeclared": "MIT",
            "licenseInfoFromFiles": [
                "NOASSERTION"
            ],
            "name": "rauc-conf.tar.gz",
            "packageFileName": "rauc-conf.tar.gz",
            "packageVerificationCode": {
                "packageVerificationCodeValue": "e384fddf8ee371764b1857bbffab2f9f56eb83ea"
            }
        }
    ],
    "files": [
        {
            "SPDXID": "SPDXRef-item600705",
            "checksums": [
                {
                    "algorithm": "SHA1",
                    "checksumValue": "aaeaaea1039dcad33897e2793ab651cfaf3e06da"
                },
                {
                    "algorithm": "SHA256",
                    "checksumValue": "2bd4bb3c06d0d1a7772142b5efd2d24dfdad2dda8478d92253a962bebbfaf92f"
                },
                {
                    "algorithm": "MD5",
                    "checksumValue": "a43b46a1e4a8854cf1978d40ff7b50f3"
                }
            ],
            "copyrightText": "NOASSERTION",
            "fileName": "rauc-conf.tar.gz/rauc-conf.tar/tmpdir/system.conf",
            "licenseConcluded": "MIT",
            "licenseInfoInFiles": [
                "NOASSERTION"
            ]
        },
        {
            "SPDXID": "SPDXRef-item600706",
            "checksums": [
                {
                    "algorithm": "SHA1",
                    "checksumValue": "8dd40d2cf9b383a2fd2ffee4c4aaea7085f95259"
                },
                {
                    "algorithm": "SHA256",
                    "checksumValue": "3c21cbe70320b11767ac0a7d4d799e5b0978ae0aa84d5cc7edded04cc40fdcab"
                },
                {
                    "algorithm": "MD5",
                    "checksumValue": "6ee943eebe1e356c04dcfcbab8c193ab"
                }
            ],
            "copyrightText": "NOASSERTION",
            "fileName": "rauc-conf.tar.gz/rauc-conf.tar/tmpdir/system_nand.conf",
            "licenseConcluded": "NOASSERTION",
            "licenseInfoInFiles": [
                "NOASSERTION"
            ]
        },
        {
            "SPDXID": "SPDXRef-item600708",
            "checksums": [
                {
                    "algorithm": "SHA1",
                    "checksumValue": "ca2dec782b6ed5c767ebfef044fce84912f35194"
                },
                {
                    "algorithm": "SHA256",
                    "checksumValue": "af95042decb01325adf27a41d665db8df7ceda4d11661a83f99b845fb664b37b"
                },
                {
                    "algorithm": "MD5",
                    "checksumValue": "03a560da56e8c11daf2026e24bb0dbbb"
                }
            ],
            "copyrightText": "NOASSERTION",
            "fileName": "rauc-conf.tar.gz/rauc-conf.tar/tmpdir/mainca-rsa.crt.pem",
            "licenseConcluded": "NOASSERTION",
            "licenseInfoInFiles": [
                "NOASSERTION"
            ]
        }
    ],
    "relationships": [
        {
            "spdxElementId": "SPDXRef-DOCUMENT",
            "relatedSpdxElement": "SPDXRef-upload144",
            "relationshipType": "DESCRIBES"
        },
        {
            "spdxElementId": "SPDXRef-upload144",
            "relatedSpdxElement": "SPDXRef-item600705",
            "relationshipType": "CONTAINS"
        },
        {
            "spdxElementId": "SPDXRef-upload144",
            "relatedSpdxElement": "SPDXRef-item600706",
            "relationshipType": "CONTAINS"
        },
        {
            "spdxElementId": "SPDXRef-upload144",
            "relatedSpdxElement": "SPDXRef-item600708",
            "relationshipType": "CONTAINS"
        }
    ]
}